{"info":{},"errors_good":{"2":"2667040","0":"142775435","no_match":"1398825"},"pass":1,"distribution_good":{"6":"18859710","3":"21519115","7":"16807789","168":"634837","2":"17923113","8":"18097953","1":"15718151","4":"16802678","5":"19079129"},"position":"3","distribution_all":{"6":"20198076","3":"23183996","7":"18246956","168":"680086","2":"19283634","8":"19490566","1":"16998544","4":"18176243","5":"20482131"},"id_run":"6624","__CLASS__":"npg_qc::autoqc::results::tag_decode_stats-56.1","errors_all":{"1":"4369085","0":"152371147","no_match":"2965539"},"tag_code":{"6":"GCCAATGT","3":"TTAGGCAT","7":"CAGATCTG","168":"ACAACGCA","2":"CGATGTTT","8":"ACTTGATG","1":"ATCACGTT","4":"TGACCACT","5":"ACAGTGGT"}}
