<?xml version="1.0" encoding="utf-8"?>
<run id_run="4174" batch_id="5230" id_instrument="38" expected_cycle_count="74" actual_cycle_count="74" priority="1" id_run_pair="0" is_paired="0" is_dev="0" id_instrument_format="4" name="IL33_4174" loader="js2" loading_date="2009-12-11" run_folder="091211_IL33_4174">
 <instrument id_instrument="38" name="IL33" id_instrument_format="4" external_name="" serial="" iscurrent="0" />
 <run_lanes><run_lane id_run_lane="32960" id_run="4174" tile_count="120" tracks="2" id_project="1" projectname="FUSE" auto_analyse="1" position="1" />
<run_lane id_run_lane="32961" id_run="4174" tile_count="120" tracks="2" id_project="1" projectname="FUSE" auto_analyse="1" position="2" />
<run_lane id_run_lane="32962" id_run="4174" tile_count="120" tracks="2" id_project="1" projectname="FUSE" auto_analyse="1" position="3" />
<run_lane id_run_lane="32963" id_run="4174" tile_count="120" tracks="2" id_project="1" projectname="FUSE" auto_analyse="1" position="4" />
<run_lane id_run_lane="32964" id_run="4174" tile_count="120" tracks="2" id_project="1" projectname="FUSE" auto_analyse="1" position="5" />
<run_lane id_run_lane="32965" id_run="4174" tile_count="120" tracks="2" id_project="1" projectname="FUSE" auto_analyse="1" position="6" />
<run_lane id_run_lane="32966" id_run="4174" tile_count="120" tracks="2" id_project="1" projectname="FUSE" auto_analyse="1" position="7" />
<run_lane id_run_lane="32967" id_run="4174" tile_count="120" tracks="2" id_project="1" projectname="FUSE" auto_analyse="1" position="8" />
</run_lanes>
 <current_run_status id_run_status="58006" id_run="4174" date="2009-12-21 21:12:28" id_run_status_dict="20" id_user="7" username="pipeline" iscurrent="1" description="qc complete" />
 <run_statuses>
 <run_status id_run_status="58006" id_run="4174" date="2009-12-21 21:12:28" id_run_status_dict="20" id_user="7" username="pipeline" iscurrent="1" description="qc complete" />
 <run_status id_run_status="58005" id_run="4174" date="2009-12-21 21:12:20" id_run_status_dict="12" id_user="7" username="pipeline" iscurrent="0" description="run archived" />
 <run_status id_run_status="58004" id_run="4174" date="2009-12-21 18:08:41" id_run_status_dict="18" id_user="7" username="pipeline" iscurrent="0" description="archival in progress" />
 <run_status id_run_status="58003" id_run="4174" date="2009-12-21 17:55:35" id_run_status_dict="17" id_user="54" username="pipeline" iscurrent="0" description="archival pending" />
 <run_status id_run_status="57783" id_run="4174" date="2009-12-16 11:03:19" id_run_status_dict="19" id_user="7" username="pipeline" iscurrent="0" description="qc review pending" />
 <run_status id_run_status="57767" id_run="4174" date="2009-12-15 23:31:31" id_run_status_dict="9" id_user="7" username="pipeline" iscurrent="0" description="analysis complete" />
 <run_status id_run_status="57732" id_run="4174" date="2009-12-15 11:54:38" id_run_status_dict="7" id_user="7" username="pipeline" iscurrent="0" description="analysis in progress" />
 <run_status id_run_status="57731" id_run="4174" date="2009-12-15 11:54:03" id_run_status_dict="6" id_user="7" username="pipeline" iscurrent="0" description="analysis pending" />
 <run_status id_run_status="57730" id_run="4174" date="2009-12-15 11:54:02" id_run_status_dict="11" id_user="7" username="pipeline" iscurrent="0" description="run mirrored" />
 <run_status id_run_status="57716" id_run="4174" date="2009-12-15 08:31:06" id_run_status_dict="4" id_user="7" username="pipeline" iscurrent="0" description="run complete" />
 <run_status id_run_status="57552" id_run="4174" date="2009-12-11 12:08:58" id_run_status_dict="2" id_user="7" username="pipeline" iscurrent="0" description="run in progress" />
 <run_status id_run_status="57551" id_run="4174" date="2009-12-11 11:56:13" id_run_status_dict="1" id_user="15" username="pipeline" iscurrent="0" description="run pending" />
 </run_statuses>
 <annotations>
 <annotation id_run_annotation="6573" id_run="4174" id_annotation="6887" date="2009-12-12 10:46:22" id_user="9" username="ah1" comment="No problems seen at this point. Now on C20/74." attachment_name="" run_current_ok="" current_cycle="" />
 <annotation id_run_annotation="6676" id_run="4174" id_annotation="6993" date="2009-12-21 17:53:00" id_user="54" username="svvd" comment="37 cyc PE run: PASS. Yield of 16.6 Gbases. %Error rates of 0.1 (R1) and 0.2 (R2). " attachment_name="" run_current_ok="" current_cycle="" />
 <annotation id_run_annotation="6677" id_run="4174" id_annotation="6994" date="2009-12-21 17:55:23" id_user="54" username="svvd" comment="Yet to be Qced on S&#x27;Scape - there seems to be a problem." attachment_name="" run_current_ok="" current_cycle="" />
 <annotation id_run_annotation="6680" id_run="4174" id_annotation="7002" date="2009-12-22 14:33:03" id_user="54" username="svvd" comment="Qced on S&#x27;Scape." attachment_name="" run_current_ok="" current_cycle="" />
 </annotations>
 <tags>
   <tag id_tag="17" description="paired_read" />
   <tag id_tag="16" description="rta" />
 </tags>
</run>
